capacity_web/__init__.py
capacity_web-1.0.6.dist-info/METADATA
capacity_web-1.0.6.dist-info/WHEEL
capacity_web-1.0.6.dist-info/RECORD
