Metadata-Version: 2.4
Name: capacity-web
Version: 1.0.6
Summary: 网络搜索功能包，提供简单易用的网络搜索接口
Project-URL: Homepage, https://github.com/capacity/capacity-web
Project-URL: Repository, https://github.com/capacity/capacity-web.git
Project-URL: Issues, https://github.com/capacity/capacity-web/issues
Author-email: simen <hi@simen.ai>
Keywords: api,capacity,http,network,scraping,search,simen,web-search
Classifier: Development Status :: 4 - Beta
Classifier: Intended Audience :: Developers
Classifier: License :: OSI Approved :: MIT License
Classifier: Programming Language :: Python :: 3
Classifier: Programming Language :: Python :: 3.8
Classifier: Programming Language :: Python :: 3.9
Classifier: Programming Language :: Python :: 3.10
Classifier: Programming Language :: Python :: 3.11
Classifier: Programming Language :: Python :: 3.12
Requires-Python: >=3.8
Requires-Dist: httpx>=0.24.0
Requires-Dist: tenacity>=8.0.0
